camel_case_switcher/__init__.py
camel_case_switcher/_impl_fallback.py
camel_case_switcher/_impl_regex.py
camel_case_switcher/deprecated.py
camel_case_switcher/dict_processor.py
camel_case_switcher/string_processor.py
camel_case_switcher-2.1.0.dist-info/LICENSE.txt
camel_case_switcher-2.1.0.dist-info/METADATA
camel_case_switcher-2.1.0.dist-info/WHEEL
camel_case_switcher-2.1.0.dist-info/top_level.txt
camel_case_switcher-2.1.0.dist-info/RECORD
